Workbook

Sheet Raw Data
A1: Order ID | B1: Order Date | C1: Product | D1: Category | E1: Region | F1: Customer | G1: Quantity | H1: Unit Price | I1: Sales | J1: Cost | K1: Profit | L1: Month
A2: ORD-0514 | B2: 45658 | C2: Notebook | D2: Office Supplies | E2: East | F2: Customer 126 | G2: 4 | H2: 971.69 | I2: 3886.76 | J2: 2909.63 | K2: 977.13 | L2: =TEXT(B2,"mmm-yyyy") -> Jan-2025
A3: ORD-0552 | B3: 45658 | C3: Smartphone | D3: Electronics | E3: North | F3: Customer 090 | G3: 2 | H3: 9573.29 | I3: 19146.58 | J3: 15423.08 | K3: 3723.5 | L3: =TEXT(B3,"mmm-yyyy") -> Jan-2025
A4: ORD-1187 | B4: 45658 | C4: Table Lamp | D4: Furniture | E4: South | F4: Customer 183 | G4: 3 | H4: 16197.32 | I4: 48591.96 | J4: 40637.79 | K4: 7954.17 | L4: =TEXT(B4,"mmm-yyyy") -> Jan-2025
A5: ORD-1034 | B5: 45658 | C5: Pens | D5: Office Supplies | E5: West | F5: Customer 206 | G5: 5 | H5: 651.37 | I5: 3256.85 | J5: 2657.58 | K5: 599.27 | L5: =TEXT(B5,"mmm-yyyy") -> Jan-2025
A6: ORD-0771 | B6: 45659 | C6: Monitor | D6: Electronics | E6: West | F6: Customer 131 | G6: 1 | H6: 32729.48 | I6: 32729.48 | J6: 29032.21 | K6: 3697.27 | L6: =TEXT(B6,"mmm-yyyy") -> Jan-2025
A7: ORD-0097 | B7: 45659 | C7: Printer Paper | D7: Office Supplies | E7: West | F7: Customer 005 | G7: 5 | H7: 545.64 | I7: 2728.2 | J7: 2045.19 | K7: 683.01 | L7: =TEXT(B7,"mmm-yyyy") -> Jan-2025
A8: ORD-0510 | B8: 45659 | C8: Tablet | D8: Electronics | E8: North | F8: Customer 239 | G8: 5 | H8: 33982.32 | I8: 169911.6 | J8: 139399.12 | K8: 30512.48 | L8: =TEXT(B8,"mmm-yyyy") -> Jan-2025
A9: ORD-0924 | B9: 45659 | C9: USB Cable | D9: Accessories | E9: West | F9: Customer 191 | G9: 6 | H9: 3931.02 | I9: 23586.12 | J9: 19865.23 | K9: 3720.89 | L9: =TEXT(B9,"mmm-yyyy") -> Jan-2025
A10: ORD-0974 | B10: 45660 | C10: Tablet | D10: Electronics | E10: West | F10: Customer 124 | G10: 7 | H10: 34493.97 | I10: 241457.79 | J10: 200859.45 | K10: 40598.34 | L10: =TEXT(B10,"mmm-yyyy") -> Jan-2025
A11: ORD-0992 | B11: 45661 | C11: Calculator | D11: Office Supplies | E11: South | F11: Customer 214 | G11: 3 | H11: 1046.04 | I11: 3138.12 | J11: 2506.87 | K11: 631.25 | L11: =TEXT(B11,"mmm-yyyy") -> Jan-2025
A12: ORD-0980 | B12: 45661 | C12: Webcam | D12: Accessories | E12: West | F12: Customer 208 | G12: 2 | H12: 3207.13 | I12: 6414.26 | J12: 5220.9 | K12: 1193.36 | L12: =TEXT(B12,"mmm-yyyy") -> Jan-2025
A13: ORD-0308 | B13: 45661 | C13: Printer Paper | D13: Office Supplies | E13: North | F13: Customer 181 | G13: 1 | H13: 721.78 | I13: 721.78 | J13: 499.28 | K13: 222.5 | L13: =TEXT(B13,"mmm-yyyy") -> Jan-2025
... A1201: ORD-0381 | B1201: 46022 | C1201: Calculator | D1201: Office Supplies | E1201: West | F1201: Customer 039 | G1201: 5 | H1201: 789.72 | I1201: 3948.6 | J1201: 2772.58 | K1201: 1176.02 | L1201: =TEXT(B1201,"mmm-yyyy") -> Dec-2025

Sheet Cleaned Data
A1: Order ID | B1: Order Date | C1: Product | D1: Category | E1: Region | F1: Customer | G1: Quantity | H1: Unit Price | I1: Sales | J1: Cost | K1: Profit | L1: Month
A2: ORD-0514 | B2: 45658 | C2: Notebook | D2: Office Supplies | E2: East | F2: Customer 126 | G2: 4 | H2: 971.69 | I2: 3886.76 | J2: 2909.63 | K2: 977.13 | L2: =TEXT(B2,"mmm-yyyy") -> Jan-2025
A3: ORD-0552 | B3: 45658 | C3: Smartphone | D3: Electronics | E3: North | F3: Customer 090 | G3: 2 | H3: 9573.29 | I3: 19146.58 | J3: 15423.08 | K3: 3723.5 | L3: =TEXT(B3,"mmm-yyyy") -> Jan-2025
A4: ORD-1187 | B4: 45658 | C4: Table Lamp | D4: Furniture | E4: South | F4: Customer 183 | G4: 3 | H4: 16197.32 | I4: 48591.96 | J4: 40637.79 | K4: 7954.17 | L4: =TEXT(B4,"mmm-yyyy") -> Jan-2025
A5: ORD-1034 | B5: 45658 | C5: Pens | D5: Office Supplies | E5: West | F5: Customer 206 | G5: 5 | H5: 651.37 | I5: 3256.85 | J5: 2657.58 | K5: 599.27 | L5: =TEXT(B5,"mmm-yyyy") -> Jan-2025
A6: ORD-0771 | B6: 45659 | C6: Monitor | D6: Electronics | E6: West | F6: Customer 131 | G6: 1 | H6: 32729.48 | I6: 32729.48 | J6: 29032.21 | K6: 3697.27 | L6: =TEXT(B6,"mmm-yyyy") -> Jan-2025
A7: ORD-0097 | B7: 45659 | C7: Printer Paper | D7: Office Supplies | E7: West | F7: Customer 005 | G7: 5 | H7: 545.64 | I7: 2728.2 | J7: 2045.19 | K7: 683.01 | L7: =TEXT(B7,"mmm-yyyy") -> Jan-2025
A8: ORD-0510 | B8: 45659 | C8: Tablet | D8: Electronics | E8: North | F8: Customer 239 | G8: 5 | H8: 33982.32 | I8: 169911.6 | J8: 139399.12 | K8: 30512.48 | L8: =TEXT(B8,"mmm-yyyy") -> Jan-2025
A9: ORD-0924 | B9: 45659 | C9: USB Cable | D9: Accessories | E9: West | F9: Customer 191 | G9: 6 | H9: 3931.02 | I9: 23586.12 | J9: 19865.23 | K9: 3720.89 | L9: =TEXT(B9,"mmm-yyyy") -> Jan-2025
A10: ORD-0974 | B10: 45660 | C10: Tablet | D10: Electronics | E10: West | F10: Customer 124 | G10: 7 | H10: 34493.97 | I10: 241457.79 | J10: 200859.45 | K10: 40598.34 | L10: =TEXT(B10,"mmm-yyyy") -> Jan-2025
A11: ORD-0992 | B11: 45661 | C11: Calculator | D11: Office Supplies | E11: South | F11: Customer 214 | G11: 3 | H11: 1046.04 | I11: 3138.12 | J11: 2506.87 | K11: 631.25 | L11: =TEXT(B11,"mmm-yyyy") -> Jan-2025
A12: ORD-0980 | B12: 45661 | C12: Webcam | D12: Accessories | E12: West | F12: Customer 208 | G12: 2 | H12: 3207.13 | I12: 6414.26 | J12: 5220.9 | K12: 1193.36 | L12: =TEXT(B12,"mmm-yyyy") -> Jan-2025
A13: ORD-0308 | B13: 45661 | C13: Printer Paper | D13: Office Supplies | E13: North | F13: Customer 181 | G13: 1 | H13: 721.78 | I13: 721.78 | J13: 499.28 | K13: 222.5 | L13: =TEXT(B13,"mmm-yyyy") -> Jan-2025
... A1201: ORD-0381 | B1201: 46022 | C1201: Calculator | D1201: Office Supplies | E1201: West | F1201: Customer 039 | G1201: 5 | H1201: 789.72 | I1201: 3948.6 | J1201: 2772.58 | K1201: 1176.02 | L1201: =TEXT(B1201,"mmm-yyyy") -> Dec-2025

Sheet Monthly Profit

Sheet Top Products

Sheet Regional Performance

Sheet Category Performance

Sheet Monthly Sales

Sheet Analysis
A1: KPI | B1: Value
A2: Total Sales | B2: =SUM('Cleaned Data'!I2:I1201) -> 73765647
A3: Total Profit | B3: =SUM('Cleaned Data'!K2:K1201) -> 11320295
A4: Total Orders | B4: =COUNTA('Cleaned Data'!A2:A1201) -> 1200
A5: Total Quantity | B5: =SUM('Cleaned Data'!G2:G1201) -> 4898
A6: Average Order Value | B6: =B2/B4 -> 61471.373

Sheet Dashboard
A1: SALES DASHBOARD
A2: Business Sales Performance — 2025
A4: TOTAL SALES | C4: TOTAL PROFIT | E4: TOTAL ORDERS
A5: =Analysis!B2 -> 73765647 | C5: =Analysis!B3 -> 11320295 | E5: =Analysis!B4 -> 1200
A8: TOTAL QUANTITY | C8: AVERAGE ORDER VALUE
A9: =Analysis!B5 -> 4898 | C9: =Analysis!B6 -> 61471.373
A47: KEY BUSINESS INSIGHTS
A51: 1)Accessories generated the highest sales among all product categories, indicating strong customer demand for this category.
A53: 2)South region recorded the highest sales, making it the strongest-performing region in the dataset.
A55: 3)April 2025 recorded the highest monthly sales, showing a peak in sales performance during this month.
A57: 4)Monitor was the top-selling product based on sales, making it an important product for the business.
A59: 5)East region had the lowest sales among the identified regions. Some records were classified as "Unknown" because the region information was missing in the original data.
